grizzlo/__init__.py
grizzlo/engine.py
grizzlo-0.1.1.dist-info/METADATA
grizzlo-0.1.1.dist-info/WHEEL
grizzlo-0.1.1.dist-info/top_level.txt
grizzlo-0.1.1.dist-info/RECORD
