Metadata-Version: 2.1
Name: grizzlo
Version: 0.1.1
Summary: High-performance, scalable Pandas-compatible analytics library
Home-page: https://github.com/datwithshah/grizzlo
Author: Your Name
Author-email: datawithshah@gmail.com
License: UNKNOWN
Platform: UNKNOWN
Classifier: Programming Language :: Python :: 3
Classifier: License :: OSI Approved :: MIT License
Classifier: Operating System :: OS Independent
Requires-Python: >=3.7
Requires-Dist: pandas (<2.0.0,>=1.3.0)
Requires-Dist: matplotlib (>=3.0.0)
Requires-Dist: numpy (>=1.18.0)
